proxyllm/__init__.py
proxyllm/cli.py
proxyllm/config/__init__.py
proxyllm/config/internal_config.py
proxyllm/data/__init__.py
proxyllm/data/tokenizer-wiki.json
proxyllm/provider/__init__.py
proxyllm/provider/anthropic/__init__.py
proxyllm/provider/anthropic/claude.py
proxyllm/provider/base.py
proxyllm/provider/cohere/__init__.py
proxyllm/provider/cohere/cohere.py
proxyllm/provider/google/__init__.py
proxyllm/provider/google/vertexai.py
proxyllm/provider/huggingface/__init__.py
proxyllm/provider/huggingface/llama2.py
proxyllm/provider/mistral/__init__.py
proxyllm/provider/mistral/mistral.py
proxyllm/provider/openai/__init__.py
proxyllm/provider/openai/chatgpt.py
proxyllm/proxyllm.py
proxyllm/utils/__init__.py
proxyllm/utils/categorization.py
proxyllm/utils/cost.py
proxyllm/utils/enums.py
proxyllm/utils/exceptions/llmproxy_client.py
proxyllm/utils/exceptions/provider.py
proxyllm/utils/proxy_logger.py
proxyllm/utils/sorting.py
proxyllm/utils/timeout_function.py
proxyllm/utils/tokenizer.py
proxyllm-0.2.3.dist-info/LICENSE
proxyllm-0.2.3.dist-info/METADATA
proxyllm-0.2.3.dist-info/WHEEL
proxyllm-0.2.3.dist-info/entry_points.txt
proxyllm-0.2.3.dist-info/RECORD
