Metadata-Version: 2.1
Name: proxyllm
Version: 0.2.3
Summary: LLM Proxy to reduce cost and complexity of using multiple LLMs
Requires-Python: >=3.11,<4.0
Classifier: Programming Language :: Python :: 3
Classifier: Programming Language :: Python :: 3.11
Classifier: Programming Language :: Python :: 3.12
Requires-Dist: anthropic (>=0.20.0,<0.21.0)
Requires-Dist: click (>=8.1.7,<9.0.0)
Requires-Dist: cohere (>=5.5.3,<6.0.0)
Requires-Dist: google-cloud-aiplatform (>=1.35.0,<2.0.0)
Requires-Dist: mistralai (>=0.1.8,<0.2.0)
Requires-Dist: openai (>=1.11.1,<2.0.0)
Requires-Dist: python-dotenv (>=1.0.0,<2.0.0)
Requires-Dist: tiktoken (>=0.7.0,<0.8.0)
Requires-Dist: torch (>=2.2.1,<3.0.0)
Requires-Dist: transformers (>=4.38.2,<5.0.0)
